[
  {
    "__TYPE__": "SharedSliceContent",
    "variation": "default",
    "primary": {
      "title": {
        "__TYPE__": "StructuredTextContent",
        "value": [{ "type": "heading2", "content": { "text": "Sudden" } }]
      },
      "subtitle": {
        "__TYPE__": "StructuredTextContent",
        "value": [{ "type": "heading3", "content": { "text": "Necessary" } }]
      },
      "description": {
        "__TYPE__": "StructuredTextContent",
        "value": [
          {
            "type": "paragraph",
            "content": {
              "text": "Do tempor et ipsum eu elit aliquip laborum velit excepteur minim cillum nisi officia in. Ipsum exercitation sunt deserunt ex aute incididunt aliquip. In do quis eiusmod culpa excepteur ullamco non."
            }
          }
        ]
      },
      "backgroundcolor": {
        "__TYPE__": "FieldContent",
        "value": "#d9e3f0",
        "type": "Color"
      }
    },
    "items": [
      {
        "__TYPE__": "GroupItemContent",
        "value": [
          [
            "series",
            {
              "__TYPE__": "LinkContent",
              "value": { "__TYPE__": "DocumentLink", "id": "mock_document_id" }
            }
          ]
        ]
      }
    ]
  }
]
